[{"": "0", "track_id": "4hsEFcCA7AL5hlKG4PRp2Z", "track_name": "Michi Teyu Ku (Overflowing)", "href": "https://api.spotify.com/v1/tracks/4hsEFcCA7AL5hlKG4PRp2Z", "popularity": "69", "uri": "spotify:track:4hsEFcCA7AL5hlKG4PRp2Z", "album_id": "06qRSgIo9l4Gf7ACV6JZQq", "duration": "310.9971", "loudness": "-7.91", "tempo": "143.99", "time_signature": "4/4", "key": "A", "mode": "Major", "acousticness": "0.473", "energy": "0.591", "danceability": "0.565", "speechiness": "0.0336", "instrumentalness": "0.0523", "album_name": "Michi Teyu Ku (Overflowing)", "album_type": "single", "album_popularity": "57", "release_date": "2024-03-14", "total_tracks": "1", "album_uri": "spotify:album:06qRSgIo9l4Gf7ACV6JZQq", "album_href": "https://api.spotify.com/v1/albums/06qRSgIo9l4Gf7ACV6JZQq"}, {"": "1", "track_id": "0o9zmvc5f3EFApU52PPIyW", "track_name": "Shinunoga E-Wa", "href": "https://api.spotify.com/v1/tracks/0o9zmvc5f3EFApU52PPIyW", "popularity": "78", "uri": "spotify:track:0o9zmvc5f3EFApU52PPIyW", "album_id": "1OojCidx0eoPKch2M0Kz31", "duration": "185.57333", "loudness": "-6.124", "tempo": "158.078", "time_signature": "4/4", "key": "F#/Gb", "mode": "Minor", "acousticness": "0.166", "energy": "0.76", "danceability": "0.6", "speechiness": "0.0452", "instrumentalness": "4.09e-05", "album_name": "HELP EVER HURT NEVER", "album_type": "album", "album_popularity": "67", "release_date": "2020-05-20", "total_tracks": "11", "album_uri": "spotify:album:1OojCidx0eoPKch2M0Kz31", "album_href": "https://api.spotify.com/v1/albums/1OojCidx0eoPKch2M0Kz31"}, {"": "12", "track_id": "7AMGgAPFczs3wJgMqu6Eqi", "track_name": "Matsuri", "href": "https://api.spotify.com/v1/tracks/7AMGgAPFczs3wJgMqu6Eqi", "popularity": "68", "uri": "spotify:track:7AMGgAPFczs3wJgMqu6Eqi", "album_id": "7Ip9X7pnkhJ4cwDoBnvneD", "duration": "225.92", "loudness": "-7.335", "tempo": "97.025", "time_signature": "4/4", "key": "C#/Db", "mode": "Major", "acousticness": "0.00892", "energy": "0.731", "danceability": "0.663", "speechiness": "0.0338", "instrumentalness": "0.0502", "album_name": "LOVE ALL SERVE ALL", "album_type": "album", "album_popularity": "61", "release_date": "2022-03-23", "total_tracks": "11", "album_uri": "spotify:album:7Ip9X7pnkhJ4cwDoBnvneD", "album_href": "https://api.spotify.com/v1/albums/7Ip9X7pnkhJ4cwDoBnvneD"}, {"": "13", "track_id": "51oc6MEsXTpnPn6GOw5VuP", "track_name": "\u304d\u3089\u308a", "href": "https://api.spotify.com/v1/tracks/51oc6MEsXTpnPn6GOw5VuP", "popularity": "70", "uri": "spotify:track:51oc6MEsXTpnPn6GOw5VuP", "album_id": "2OXwORzPU4tm1Skiv6l9KT", "duration": "231.88295", "loudness": "-6.833", "tempo": "116.982", "time_signature": "4/4", "key": "D", "mode": "Major", "acousticness": "0.00803", "energy": "0.764", "danceability": "0.746", "speechiness": "0.0462", "instrumentalness": "0.0", "album_name": "Kirari Remixes (Asia Edition)", "album_type": "album", "album_popularity": "58", "release_date": "2022-01-14", "total_tracks": "9", "album_uri": "spotify:album:2OXwORzPU4tm1Skiv6l9KT", "album_href": "https://api.spotify.com/v1/albums/2OXwORzPU4tm1Skiv6l9KT"}, {"": "14", "track_id": "02tNuntKQsoou5T4O8meyh", "track_name": "Hana", "href": "https://api.spotify.com/v1/tracks/02tNuntKQsoou5T4O8meyh", "popularity": "62", "uri": "spotify:track:02tNuntKQsoou5T4O8meyh", "album_id": "0v6vQ9tMopUTccn0wUvzQD", "duration": "246.69986", "loudness": "-8.203", "tempo": "123.031", "time_signature": "4/4", "key": "F", "mode": "Minor", "acousticness": "0.118", "energy": "0.716", "danceability": "0.769", "speechiness": "0.0429", "instrumentalness": "0.00659", "album_name": "Hana", "album_type": "single", "album_popularity": "50", "release_date": "2023-10-12", "total_tracks": "1", "album_uri": "spotify:album:0v6vQ9tMopUTccn0wUvzQD", "album_href": "https://api.spotify.com/v1/albums/0v6vQ9tMopUTccn0wUvzQD"}, {"": "15", "track_id": "2vMc8rqFmqs7RFi8NDx0CJ", "track_name": "Garden", "href": "https://api.spotify.com/v1/tracks/2vMc8rqFmqs7RFi8NDx0CJ", "popularity": "59", "uri": "spotify:track:2vMc8rqFmqs7RFi8NDx0CJ", "album_id": "7Ip9X7pnkhJ4cwDoBnvneD", "duration": "229.33333", "loudness": "-8.332", "tempo": "138.023", "time_signature": "4/4", "key": "E", "mode": "Major", "acousticness": "0.0932", "energy": "0.527", "danceability": "0.589", "speechiness": "0.0572", "instrumentalness": "0.000337", "album_name": "LOVE ALL SERVE ALL", "album_type": "album", "album_popularity": "61", "release_date": "2022-03-23", "total_tracks": "11", "album_uri": "spotify:album:7Ip9X7pnkhJ4cwDoBnvneD", "album_href": "https://api.spotify.com/v1/albums/7Ip9X7pnkhJ4cwDoBnvneD"}, {"": "16", "track_id": "7pTwW5yCKRx6OkByY53jbz", "track_name": "damn", "href": "https://api.spotify.com/v1/tracks/7pTwW5yCKRx6OkByY53jbz", "popularity": "58", "uri": "spotify:track:7pTwW5yCKRx6OkByY53jbz", "album_id": "7Ip9X7pnkhJ4cwDoBnvneD", "duration": "259.02667", "loudness": "-7.955", "tempo": "129.982", "time_signature": "4/4", "key": "G", "mode": "Major", "acousticness": "0.00346", "energy": "0.759", "danceability": "0.707", "speechiness": "0.0329", "instrumentalness": "3.82e-05", "album_name": "LOVE ALL SERVE ALL", "album_type": "album", "album_popularity": "61", "release_date": "2022-03-23", "total_tracks": "11", "album_uri": "spotify:album:7Ip9X7pnkhJ4cwDoBnvneD", "album_href": "https://api.spotify.com/v1/albums/7Ip9X7pnkhJ4cwDoBnvneD"}, {"": "17", "track_id": "2CbGuO0LtVvbh3umN3mDwM", "track_name": "Nan-Nan", "href": "https://api.spotify.com/v1/tracks/2CbGuO0LtVvbh3umN3mDwM", "popularity": "54", "uri": "spotify:track:2CbGuO0LtVvbh3umN3mDwM", "album_id": "1OojCidx0eoPKch2M0Kz31", "duration": "320.64", "loudness": "-7.113", "tempo": "180.065", "time_signature": "4/4", "key": "G", "mode": "Major", "acousticness": "0.394", "energy": "0.729", "danceability": "0.577", "speechiness": "0.221", "instrumentalness": "0.000156", "album_name": "HELP EVER HURT NEVER", "album_type": "album", "album_popularity": "67", "release_date": "2020-05-20", "total_tracks": "11", "album_uri": "spotify:album:1OojCidx0eoPKch2M0Kz31", "album_href": "https://api.spotify.com/v1/albums/1OojCidx0eoPKch2M0Kz31"}, {"": "18", "track_id": "0Whfa8wikSDUvtB5mzYOGH", "track_name": "Workin' Hard", "href": "https://api.spotify.com/v1/tracks/0Whfa8wikSDUvtB5mzYOGH", "popularity": "62", "uri": "spotify:track:0Whfa8wikSDUvtB5mzYOGH", "album_id": "0BsBIukVE2pUB4xmWrkeAt", "duration": "239.07098", "loudness": "-6.106", "tempo": "90.0", "time_signature": "4/4", "key": "D", "mode": "Minor", "acousticness": "0.0336", "energy": "0.664", "danceability": "0.74", "speechiness": "0.086", "instrumentalness": "0.000314", "album_name": "Workin' Hard", "album_type": "single", "album_popularity": "49", "release_date": "2023-08-24", "total_tracks": "1", "album_uri": "spotify:album:0BsBIukVE2pUB4xmWrkeAt", "album_href": "https://api.spotify.com/v1/albums/0BsBIukVE2pUB4xmWrkeAt"}, {"": "19", "track_id": "4Lrz9Fg8L1yncuCjjKjD4D", "track_name": "Hedemo Ne-Yo - LASA edit", "href": "https://api.spotify.com/v1/tracks/4Lrz9Fg8L1yncuCjjKjD4D", "popularity": "53", "uri": "spotify:track:4Lrz9Fg8L1yncuCjjKjD4D", "album_id": "7Ip9X7pnkhJ4cwDoBnvneD", "duration": "188.94667", "loudness": "-5.899", "tempo": "175.966", "time_signature": "4/4", "key": "C", "mode": "Major", "acousticness": "0.0615", "energy": "0.861", "danceability": "0.506", "speechiness": "0.15", "instrumentalness": "1.89e-05", "album_name": "LOVE ALL SERVE ALL", "album_type": "album", "album_popularity": "61", "release_date": "2022-03-23", "total_tracks": "11", "album_uri": "spotify:album:7Ip9X7pnkhJ4cwDoBnvneD", "album_href": "https://api.spotify.com/v1/albums/7Ip9X7pnkhJ4cwDoBnvneD"}, {"": "20", "track_id": "6SyvPeEmj4yBblsKIyiGqT", "track_name": "Tabiji", "href": "https://api.spotify.com/v1/tracks/6SyvPeEmj4yBblsKIyiGqT", "popularity": "52", "uri": "spotify:track:6SyvPeEmj4yBblsKIyiGqT", "album_id": "7Ip9X7pnkhJ4cwDoBnvneD", "duration": "277.02667", "loudness": "-6.752", "tempo": "172.025", "time_signature": "4/4", "key": "A", "mode": "Major", "acousticness": "0.126", "energy": "0.564", "danceability": "0.564", "speechiness": "0.0792", "instrumentalness": "3.01e-06", "album_name": "LOVE ALL SERVE ALL", "album_type": "album", "album_popularity": "61", "release_date": "2022-03-23", "total_tracks": "11", "album_uri": "spotify:album:7Ip9X7pnkhJ4cwDoBnvneD", "album_href": "https://api.spotify.com/v1/albums/7Ip9X7pnkhJ4cwDoBnvneD"}, {"": "21", "track_id": "7tnYsRepXLaNhqj4xtcWP2", "track_name": "grace", "href": "https://api.spotify.com/v1/tracks/7tnYsRepXLaNhqj4xtcWP2", "popularity": "62", "uri": "spotify:track:7tnYsRepXLaNhqj4xtcWP2", "album_id": "0i6jJH5oVQh0KL8INSSPpu", "duration": "289.54117", "loudness": "-8.765", "tempo": "108.971", "time_signature": "4/4", "key": "G", "mode": "Major", "acousticness": "0.0822", "energy": "0.685", "danceability": "0.668", "speechiness": "0.0472", "instrumentalness": "0.0257", "album_name": "grace", "album_type": "single", "album_popularity": "50", "release_date": "2022-10-09", "total_tracks": "1", "album_uri": "spotify:album:0i6jJH5oVQh0KL8INSSPpu", "album_href": "https://api.spotify.com/v1/albums/0i6jJH5oVQh0KL8INSSPpu"}, {"": "22", "track_id": "26e8ujjSpBAHhIY2ymLUT1", "track_name": "Kaerou", "href": "https://api.spotify.com/v1/tracks/26e8ujjSpBAHhIY2ymLUT1", "popularity": "53", "uri": "spotify:track:26e8ujjSpBAHhIY2ymLUT1", "album_id": "1OojCidx0eoPKch2M0Kz31", "duration": "284.48", "loudness": "-5.926", "tempo": "91.87", "time_signature": "4/4", "key": "A", "mode": "Major", "acousticness": "0.3", "energy": "0.623", "danceability": "0.589", "speechiness": "0.0326", "instrumentalness": "0.0", "album_name": "HELP EVER HURT NEVER", "album_type": "album", "album_popularity": "67", "release_date": "2020-05-20", "total_tracks": "11", "album_uri": "spotify:album:1OojCidx0eoPKch2M0Kz31", "album_href": "https://api.spotify.com/v1/albums/1OojCidx0eoPKch2M0Kz31"}, {"": "23", "track_id": "6BhO28xuLVeaWKVnd1lbCJ", "track_name": "SAYONARA Baby", "href": "https://api.spotify.com/v1/tracks/6BhO28xuLVeaWKVnd1lbCJ", "popularity": "52", "uri": "spotify:track:6BhO28xuLVeaWKVnd1lbCJ", "album_id": "1OojCidx0eoPKch2M0Kz31", "duration": "260.53333", "loudness": "-5.579", "tempo": "132.044", "time_signature": "4/4", "key": "A", "mode": "Major", "acousticness": "0.00185", "energy": "0.884", "danceability": "0.61", "speechiness": "0.0425", "instrumentalness": "0.0", "album_name": "HELP EVER HURT NEVER", "album_type": "album", "album_popularity": "67", "release_date": "2020-05-20", "total_tracks": "11", "album_uri": "spotify:album:1OojCidx0eoPKch2M0Kz31", "album_href": "https://api.spotify.com/v1/albums/1OojCidx0eoPKch2M0Kz31"}, {"": "24", "track_id": "5cpOWNmI84MuUCeciETO64", "track_name": "Kazeyo", "href": "https://api.spotify.com/v1/tracks/5cpOWNmI84MuUCeciETO64", "popularity": "46", "uri": "spotify:track:5cpOWNmI84MuUCeciETO64", "album_id": "1OojCidx0eoPKch2M0Kz31", "duration": "284.52", "loudness": "-8.285", "tempo": "114.966", "time_signature": "3/4", "key": "A", "mode": "Minor", "acousticness": "0.679", "energy": "0.462", "danceability": "0.512", "speechiness": "0.0304", "instrumentalness": "0.000216", "album_name": "HELP EVER HURT NEVER", "album_type": "album", "album_popularity": "67", "release_date": "2020-05-20", "total_tracks": "11", "album_uri": "spotify:album:1OojCidx0eoPKch2M0Kz31", "album_href": "https://api.spotify.com/v1/albums/1OojCidx0eoPKch2M0Kz31"}, {"": "25", "track_id": "2PDtvT5DEamQTM5qeiTDsR", "track_name": "\"Seishun Sick\"", "href": "https://api.spotify.com/v1/tracks/2PDtvT5DEamQTM5qeiTDsR", "popularity": "48", "uri": "spotify:track:2PDtvT5DEamQTM5qeiTDsR", "album_id": "7Ip9X7pnkhJ4cwDoBnvneD", "duration": "324.14667", "loudness": "-6.628", "tempo": "108.024", "time_signature": "4/4", "key": "C#/Db", "mode": "Major", "acousticness": "0.151", "energy": "0.798", "danceability": "0.669", "speechiness": "0.0498", "instrumentalness": "8.55e-05", "album_name": "LOVE ALL SERVE ALL", "album_type": "album", "album_popularity": "61", "release_date": "2022-03-23", "total_tracks": "11", "album_uri": "spotify:album:7Ip9X7pnkhJ4cwDoBnvneD", "album_href": "https://api.spotify.com/v1/albums/7Ip9X7pnkhJ4cwDoBnvneD"}, {"": "26", "track_id": "57u1FaZlztApkcT5x5XNuD", "track_name": "YASASHISA", "href": "https://api.spotify.com/v1/tracks/57u1FaZlztApkcT5x5XNuD", "popularity": "50", "uri": "spotify:track:57u1FaZlztApkcT5x5XNuD", "album_id": "1OojCidx0eoPKch2M0Kz31", "duration": "240.08", "loudness": "-6.825", "tempo": "133.858", "time_signature": "4/4", "key": "C#/Db", "mode": "Major", "acousticness": "0.111", "energy": "0.707", "danceability": "0.596", "speechiness": "0.049", "instrumentalness": "0.0", "album_name": "HELP EVER HURT NEVER", "album_type": "album", "album_popularity": "67", "release_date": "2020-05-20", "total_tracks": "11", "album_uri": "spotify:album:1OojCidx0eoPKch2M0Kz31", "album_href": "https://api.spotify.com/v1/albums/1OojCidx0eoPKch2M0Kz31"}, {"": "27", "track_id": "1JRNrJKTQhfvxII8kkIcAQ", "track_name": "Mo-Eh-Wa", "href": "https://api.spotify.com/v1/tracks/1JRNrJKTQhfvxII8kkIcAQ", "popularity": "50", "uri": "spotify:track:1JRNrJKTQhfvxII8kkIcAQ", "album_id": "1OojCidx0eoPKch2M0Kz31", "duration": "301.93332", "loudness": "-7.969", "tempo": "81.973", "time_signature": "4/4", "key": "A", "mode": "Major", "acousticness": "0.43", "energy": "0.585", "danceability": "0.629", "speechiness": "0.0572", "instrumentalness": "0.0", "album_name": "HELP EVER HURT NEVER", "album_type": "album", "album_popularity": "67", "release_date": "2020-05-20", "total_tracks": "11", "album_uri": "spotify:album:1OojCidx0eoPKch2M0Kz31", "album_href": "https://api.spotify.com/v1/albums/1OojCidx0eoPKch2M0Kz31"}, {"": "28", "track_id": "1LjZnfncDtrn5YtbU4lQMf", "track_name": "\u3078\u3067\u3082\u306d\u30fc\u3088", "href": "https://api.spotify.com/v1/tracks/1LjZnfncDtrn5YtbU4lQMf", "popularity": "50", "uri": "spotify:track:1LjZnfncDtrn5YtbU4lQMf", "album_id": "7grlPzIHgZINOD2GhYBROR", "duration": "190.75452", "loudness": "-6.206", "tempo": "175.978", "time_signature": "4/4", "key": "A", "mode": "Minor", "acousticness": "0.0124", "energy": "0.818", "danceability": "0.468", "speechiness": "0.0512", "instrumentalness": "4.26e-06", "album_name": "\u3078\u3067\u3082\u306d\u30fc\u3088", "album_type": "single", "album_popularity": "38", "release_date": "2020-10-30", "total_tracks": "1", "album_uri": "spotify:album:7grlPzIHgZINOD2GhYBROR", "album_href": "https://api.spotify.com/v1/albums/7grlPzIHgZINOD2GhYBROR"}, {"": "29", "track_id": "6AJppuCk5EE86paOdDI4yL", "track_name": "Tokuninai", "href": "https://api.spotify.com/v1/tracks/6AJppuCk5EE86paOdDI4yL", "popularity": "48", "uri": "spotify:track:6AJppuCk5EE86paOdDI4yL", "album_id": "1OojCidx0eoPKch2M0Kz31", "duration": "205.25333", "loudness": "-6.613", "tempo": "99.035", "time_signature": "4/4", "key": "G", "mode": "Major", "acousticness": "0.0374", "energy": "0.563", "danceability": "0.727", "speechiness": "0.0272", "instrumentalness": "6.43e-05", "album_name": "HELP EVER HURT NEVER", "album_type": "album", "album_popularity": "67", "release_date": "2020-05-20", "total_tracks": "11", "album_uri": "spotify:album:1OojCidx0eoPKch2M0Kz31", "album_href": "https://api.spotify.com/v1/albums/1OojCidx0eoPKch2M0Kz31"}, {"": "30", "track_id": "7nhXN2H8h3i2PaHPXb6FO3", "track_name": "Kirari", "href": "https://api.spotify.com/v1/tracks/7nhXN2H8h3i2PaHPXb6FO3", "popularity": "50", "uri": "spotify:track:7nhXN2H8h3i2PaHPXb6FO3", "album_id": "7Ip9X7pnkhJ4cwDoBnvneD", "duration": "227.89333", "loudness": "-6.842", "tempo": "116.975", "time_signature": "4/4", "key": "D", "mode": "Major", "acousticness": "0.00704", "energy": "0.773", "danceability": "0.752", "speechiness": "0.0441", "instrumentalness": "0.0", "album_name": "LOVE ALL SERVE ALL", "album_type": "album", "album_popularity": "61", "release_date": "2022-03-23", "total_tracks": "11", "album_uri": "spotify:album:7Ip9X7pnkhJ4cwDoBnvneD", "album_href": "https://api.spotify.com/v1/albums/7Ip9X7pnkhJ4cwDoBnvneD"}, {"": "31", "track_id": "3DyekzXIo7Or5Krd0eAmo5", "track_name": "YABA", "href": "https://api.spotify.com/v1/tracks/3DyekzXIo7Or5Krd0eAmo5", "popularity": "47", "uri": "spotify:track:3DyekzXIo7Or5Krd0eAmo5", "album_id": "7Ip9X7pnkhJ4cwDoBnvneD", "duration": "251.88", "loudness": "-7.699", "tempo": "126.106", "time_signature": "4/4", "key": "B", "mode": "Major", "acousticness": "0.179", "energy": "0.698", "danceability": "0.657", "speechiness": "0.0679", "instrumentalness": "0.000119", "album_name": "LOVE ALL SERVE ALL", "album_type": "album", "album_popularity": "61", "release_date": "2022-03-23", "total_tracks": "11", "album_uri": "spotify:album:7Ip9X7pnkhJ4cwDoBnvneD", "album_href": "https://api.spotify.com/v1/albums/7Ip9X7pnkhJ4cwDoBnvneD"}, {"": "32", "track_id": "2Q0LpnMDXazZk49AWEiHE2", "track_name": "Lonely Rhapsody", "href": "https://api.spotify.com/v1/tracks/2Q0LpnMDXazZk49AWEiHE2", "popularity": "47", "uri": "spotify:track:2Q0LpnMDXazZk49AWEiHE2", "album_id": "7Ip9X7pnkhJ4cwDoBnvneD", "duration": "286.64", "loudness": "-8.788", "tempo": "150.004", "time_signature": "4/4", "key": "F", "mode": "Minor", "acousticness": "0.122", "energy": "0.635", "danceability": "0.598", "speechiness": "0.0426", "instrumentalness": "0.0032", "album_name": "LOVE ALL SERVE ALL", "album_type": "album", "album_popularity": "61", "release_date": "2022-03-23", "total_tracks": "11", "album_uri": "spotify:album:7Ip9X7pnkhJ4cwDoBnvneD", "album_href": "https://api.spotify.com/v1/albums/7Ip9X7pnkhJ4cwDoBnvneD"}, {"": "33", "track_id": "7i5pytF8KaId51lIzatwdg", "track_name": "Kiri Ga Naikara", "href": "https://api.spotify.com/v1/tracks/7i5pytF8KaId51lIzatwdg", "popularity": "48", "uri": "spotify:track:7i5pytF8KaId51lIzatwdg", "album_id": "1OojCidx0eoPKch2M0Kz31", "duration": "217.61333", "loudness": "-7.121", "tempo": "98.983", "time_signature": "4/4", "key": "B", "mode": "Minor", "acousticness": "0.0246", "energy": "0.78", "danceability": "0.699", "speechiness": "0.0505", "instrumentalness": "0.0", "album_name": "HELP EVER HURT NEVER", "album_type": "album", "album_popularity": "67", "release_date": "2020-05-20", "total_tracks": "11", "album_uri": "spotify:album:1OojCidx0eoPKch2M0Kz31", "album_href": "https://api.spotify.com/v1/albums/1OojCidx0eoPKch2M0Kz31"}, {"": "34", "track_id": "2fMdT98JpheoBh6t8DBSjI", "track_name": "MO-EH-YO (Ignite)", "href": "https://api.spotify.com/v1/tracks/2fMdT98JpheoBh6t8DBSjI", "popularity": "47", "uri": "spotify:track:2fMdT98JpheoBh6t8DBSjI", "album_id": "7Ip9X7pnkhJ4cwDoBnvneD", "duration": "277.42667", "loudness": "-6.106", "tempo": "137.934", "time_signature": "4/4", "key": "C", "mode": "Major", "acousticness": "0.00144", "energy": "0.875", "danceability": "0.616", "speechiness": "0.0442", "instrumentalness": "2.82e-05", "album_name": "LOVE ALL SERVE ALL", "album_type": "album", "album_popularity": "61", "release_date": "2022-03-23", "total_tracks": "11", "album_uri": "spotify:album:7Ip9X7pnkhJ4cwDoBnvneD", "album_href": "https://api.spotify.com/v1/albums/7Ip9X7pnkhJ4cwDoBnvneD"}, {"": "37", "track_id": "74Zrps4gc3qTF49oKpm6zF", "track_name": "Cho Si Noccha Te", "href": "https://api.spotify.com/v1/tracks/74Zrps4gc3qTF49oKpm6zF", "popularity": "45", "uri": "spotify:track:74Zrps4gc3qTF49oKpm6zF", "album_id": "1OojCidx0eoPKch2M0Kz31", "duration": "282.24", "loudness": "-6.469", "tempo": "143.923", "time_signature": "4/4", "key": "A", "mode": "Minor", "acousticness": "0.00838", "energy": "0.57", "danceability": "0.609", "speechiness": "0.0303", "instrumentalness": "0.0", "album_name": "HELP EVER HURT NEVER", "album_type": "album", "album_popularity": "67", "release_date": "2020-05-20", "total_tracks": "11", "album_uri": "spotify:album:1OojCidx0eoPKch2M0Kz31", "album_href": "https://api.spotify.com/v1/albums/1OojCidx0eoPKch2M0Kz31"}, {"": "38", "track_id": "4Y9QwoUwo9blH9R9C5DCnk", "track_name": "Bye for now,", "href": "https://api.spotify.com/v1/tracks/4Y9QwoUwo9blH9R9C5DCnk", "popularity": "44", "uri": "spotify:track:4Y9QwoUwo9blH9R9C5DCnk", "album_id": "7Ip9X7pnkhJ4cwDoBnvneD", "duration": "230.72", "loudness": "-13.28", "tempo": "166.043", "time_signature": "4/4", "key": "G#/Ab", "mode": "Major", "acousticness": "0.832", "energy": "0.209", "danceability": "0.251", "speechiness": "0.0363", "instrumentalness": "0.056", "album_name": "LOVE ALL SERVE ALL", "album_type": "album", "album_popularity": "61", "release_date": "2022-03-23", "total_tracks": "11", "album_uri": "spotify:album:7Ip9X7pnkhJ4cwDoBnvneD", "album_href": "https://api.spotify.com/v1/albums/7Ip9X7pnkhJ4cwDoBnvneD"}, {"": "39", "track_id": "7r9v0CLTunOwlbvdOFFgZo", "track_name": "Tsumi No Kaori", "href": "https://api.spotify.com/v1/tracks/7r9v0CLTunOwlbvdOFFgZo", "popularity": "46", "uri": "spotify:track:7r9v0CLTunOwlbvdOFFgZo", "album_id": "1OojCidx0eoPKch2M0Kz31", "duration": "214.2", "loudness": "-5.745", "tempo": "154.963", "time_signature": "4/4", "key": "B", "mode": "Minor", "acousticness": "0.0466", "energy": "0.861", "danceability": "0.517", "speechiness": "0.0644", "instrumentalness": "0.0", "album_name": "HELP EVER HURT NEVER", "album_type": "album", "album_popularity": "67", "release_date": "2020-05-20", "total_tracks": "11", "album_uri": "spotify:album:1OojCidx0eoPKch2M0Kz31", "album_href": "https://api.spotify.com/v1/albums/1OojCidx0eoPKch2M0Kz31"}, {"": "41", "track_id": "1zzJfOdraIBJtCAatSYzCt", "track_name": "Kirari - Daul Remix", "href": "https://api.spotify.com/v1/tracks/1zzJfOdraIBJtCAatSYzCt", "popularity": "50", "uri": "spotify:track:1zzJfOdraIBJtCAatSYzCt", "album_id": "2OXwORzPU4tm1Skiv6l9KT", "duration": "245.33043", "loudness": "-6.709", "tempo": "114.99", "time_signature": "4/4", "key": "G", "mode": "Major", "acousticness": "0.0511", "energy": "0.684", "danceability": "0.827", "speechiness": "0.171", "instrumentalness": "3.68e-05", "album_name": "Kirari Remixes (Asia Edition)", "album_type": "album", "album_popularity": "58", "release_date": "2022-01-14", "total_tracks": "9", "album_uri": "spotify:album:2OXwORzPU4tm1Skiv6l9KT", "album_href": "https://api.spotify.com/v1/albums/2OXwORzPU4tm1Skiv6l9KT"}, {"": "42", "track_id": "14QNjDBXGCwEzJZUKkiTem", "track_name": "\u307e\u3064\u308a", "href": "https://api.spotify.com/v1/tracks/14QNjDBXGCwEzJZUKkiTem", "popularity": "51", "uri": "spotify:track:14QNjDBXGCwEzJZUKkiTem", "album_id": "3Pwex5PyfxbrNTAwl6FGo5", "duration": "225.92404", "loudness": "-7.307", "tempo": "97.021", "time_signature": "4/4", "key": "C#/Db", "mode": "Major", "acousticness": "0.00758", "energy": "0.737", "danceability": "0.661", "speechiness": "0.0349", "instrumentalness": "0.0408", "album_name": "\u307e\u3064\u308a", "album_type": "single", "album_popularity": "39", "release_date": "2022-03-20", "total_tracks": "1", "album_uri": "spotify:album:3Pwex5PyfxbrNTAwl6FGo5", "album_href": "https://api.spotify.com/v1/albums/3Pwex5PyfxbrNTAwl6FGo5"}]